pytest_llm/__init__.py
pytest_llm/_version.py
pytest_llm/hooks.py
pytest_llm-0.1.0.dist-info/entry_points.txt
pytest_llm-0.1.0.dist-info/licenses/LICENSE
pytest_llm-0.1.0.dist-info/WHEEL
pytest_llm-0.1.0.dist-info/METADATA
pytest_llm-0.1.0.dist-info/RECORD
