Metadata-Version: 2.4
Name: pytest-llm
Version: 0.1.0
Summary: pytest-llm: A pytest plugin for testing LLM outputs with success rate thresholds.
Author-email: Johannes Maron <johannes@maron.family>
Requires-Python: >=3.10
Classifier: Development Status :: 3 - Alpha
Classifier: Framework :: Pytest
Classifier: Intended Audience :: Developers
Classifier: License :: OSI Approved :: BSD License
Classifier: Operating System :: OS Independent
Classifier: Programming Language :: Python
Classifier: Programming Language :: Python :: 3
Classifier: Programming Language :: Python :: 3.10
Classifier: Programming Language :: Python :: 3.11
Classifier: Programming Language :: Python :: 3.12
Classifier: Programming Language :: Python :: 3.13
Classifier: Topic :: Software Development :: Testing
License-File: LICENSE
Requires-Dist: pytest>=7.0.0
Requires-Dist: pre-commit ; extra == "lint"
Requires-Dist: ruff ; extra == "lint"
Requires-Dist: pytest-cov ; extra == "test"
Requires-Dist: httpx ; extra == "test"
Requires-Dist: ollama ; extra == "test"
Project-URL: Homepage, https://github.com/codingjoe/pytest-llm
Project-URL: Repository, https://github.com/codingjoe/pytest-llm
Provides-Extra: lint
Provides-Extra: test
